MANIFEST.in
README.md
setup.py
bluelens_k8s/__init__.py
bluelens_k8s/pod.py
bluelens_k8s/service.py
bluelens_k8s.egg-info/PKG-INFO
bluelens_k8s.egg-info/SOURCES.txt
bluelens_k8s.egg-info/dependency_links.txt
bluelens_k8s.egg-info/requires.txt
bluelens_k8s.egg-info/top_level.txt