Metadata-Version: 1.0
Name: bluelens-k8s
Version: 0.0.4
Summary: A utility for Kubernetes
Home-page: UNKNOWN
Author: UNKNOWN
Author-email: master@bluehack.net
License: UNKNOWN
Keywords: BlueLens,bluelens-k8s
Platform: UNKNOWN
